meetings/__init__.py
scrum_cli/__init__.py
scrum_cli/chatbot_ui.py
scrum_cli/live_transcription.py
scrum_cli/main.py
scrum_cli/memory_store.py
scrum_cli/ngrok_manager.py
scrum_cli/proxy_host.py
scrum_cli/proxy_server.py
scrum_cli/roast_engine.py
scrum_cli-1.0.0.dist-info/licenses/LICENSE
scrum_cli-1.0.0.dist-info/METADATA
scrum_cli-1.0.0.dist-info/WHEEL
scrum_cli-1.0.0.dist-info/entry_points.txt
scrum_cli-1.0.0.dist-info/top_level.txt
scrum_cli-1.0.0.dist-info/RECORD
