Metadata-Version: 2.4
Name: scrum-cli
Version: 1.0.0
Summary: AI-powered meeting assistant with real-time transcription and roast mode
Home-page: https://github.com/Rachit-Gandhi/scrum-cli
Author: Rachit Gandhi
Author-email: Rachit Gandhi <rachitgandhi2002@gmail.com>
License: MIT
Project-URL: Homepage, https://github.com/Rachit-Gandhi/scrum-cli
Project-URL: Repository, https://github.com/Rachit-Gandhi/scrum-cli
Project-URL: Issues, https://github.com/Rachit-Gandhi/scrum-cli/issues
Project-URL: Documentation, https://github.com/Rachit-Gandhi/scrum-cli/blob/main/README.md
Keywords: meeting,transcription,ai,assistant,scrum,cli,roast
Classifier: Development Status :: 4 - Beta
Classifier: Intended Audience :: Developers
Classifier: Topic :: Office/Business :: Groupware
Classifier: Topic :: Communications :: Conferencing
Classifier: License :: OSI Approved :: MIT License
Classifier: Programming Language :: Python :: 3
Classifier: Programming Language :: Python :: 3.9
Classifier: Programming Language :: Python :: 3.10
Classifier: Programming Language :: Python :: 3.11
Classifier: Programming Language :: Python :: 3.12
Requires-Python: >=3.9
License-File: LICENSE
Requires-Dist: click>=8.0.0
Requires-Dist: chromadb>=0.4.0
Requires-Dist: fastapi>=0.116.1
Requires-Dist: google-generativeai>=0.7.0
Requires-Dist: groq>=0.30.0
Requires-Dist: numpy==1.26.4
Requires-Dist: openai-whisper>=20250625
Requires-Dist: psutil>=5.9.0
Requires-Dist: pyannote-audio>=3.3.0
Requires-Dist: pydub>=0.25.1
Requires-Dist: python-dotenv==1.1.0
Requires-Dist: requests>=2.28.0
Requires-Dist: rich>=13.0.0
Requires-Dist: scikit-learn<1.7.1
Requires-Dist: selenium>=4.0.0
Requires-Dist: setuptools-rust>=1.11.1
Requires-Dist: torch>=2.7.1
Requires-Dist: torchaudio>=2.7.1
Requires-Dist: uvicorn>=0.35.0
Requires-Dist: webdriver-manager>=3.8.0
Requires-Dist: websockets>=15.0.1
Requires-Dist: onnxruntime==1.15.0
Requires-Dist: numba>=0.53.1
Provides-Extra: dev
Requires-Dist: pytest>=6.0; extra == "dev"
Requires-Dist: black; extra == "dev"
Requires-Dist: flake8; extra == "dev"
Requires-Dist: mypy; extra == "dev"
Dynamic: author
Dynamic: home-page
Dynamic: license-file
Dynamic: requires-python
